faceai_bgimpact/Nirmala.ttf
faceai_bgimpact/__init__.py
faceai_bgimpact/configs/__init__.py
faceai_bgimpact/configs/default_dcgan_config.py
faceai_bgimpact/configs/default_stylegan_config.py
faceai_bgimpact/configs/default_vae_config.py
faceai_bgimpact/configs/normalization_config.json
faceai_bgimpact/data_processing/__init__.py
faceai_bgimpact/data_processing/create_blur_and_grey.py
faceai_bgimpact/data_processing/create_masks.py
faceai_bgimpact/data_processing/download_all_ffhq.py
faceai_bgimpact/data_processing/download_raw_ffhq.py
faceai_bgimpact/data_processing/paths.py
faceai_bgimpact/main.py
faceai_bgimpact/models/__init__.py
faceai_bgimpact/models/abstract_model.py
faceai_bgimpact/models/data_loader.py
faceai_bgimpact/models/dcgan_/__init__.py
faceai_bgimpact/models/dcgan_/dcgan.py
faceai_bgimpact/models/dcgan_/discriminator.py
faceai_bgimpact/models/dcgan_/generator.py
faceai_bgimpact/models/provae/__init__.py
faceai_bgimpact/models/provae/provae.py
faceai_bgimpact/models/stylegan_/__init__.py
faceai_bgimpact/models/stylegan_/discriminator.py
faceai_bgimpact/models/stylegan_/generator.py
faceai_bgimpact/models/stylegan_/loss.py
faceai_bgimpact/models/stylegan_/stylegan.py
faceai_bgimpact/models/stylegan_/utils.py
faceai_bgimpact/models/utils.py
faceai_bgimpact/models/vae_/__init__.py
faceai_bgimpact/models/vae_/decoder.py
faceai_bgimpact/models/vae_/encoder.py
faceai_bgimpact/models/vae_/vae.py
faceai_bgimpact/scripts/create_blur_and_grey.py
faceai_bgimpact/scripts/create_masks.py
faceai_bgimpact/scripts/create_video.py
faceai_bgimpact/scripts/download_all_ffhq.py
faceai_bgimpact/scripts/graph_fids.py
faceai_bgimpact/scripts/train.py
faceai_bgimpact-0.2.4.dist-info/LICENSE
faceai_bgimpact-0.2.4.dist-info/METADATA
faceai_bgimpact-0.2.4.dist-info/WHEEL
faceai_bgimpact-0.2.4.dist-info/entry_points.txt
faceai_bgimpact-0.2.4.dist-info/RECORD
