Metadata-Version: 2.1
Name: faceai-bgimpact
Version: 0.2.4
Summary: FaceAI-BGImpact implements various generative methods and studies the impact of altering the background on the generated images and the training of the models.
Author: Thomas Kientz
Requires-Python: >=3.9,<3.12
Classifier: Programming Language :: Python :: 3
Classifier: Programming Language :: Python :: 3.9
Classifier: Programming Language :: Python :: 3.10
Classifier: Programming Language :: Python :: 3.11
Requires-Dist: imageio (==2.19.3)
Requires-Dist: imageio-ffmpeg (==0.4.7)
Requires-Dist: install (>=1.3.5,<2.0.0)
Requires-Dist: ipykernel (>=6.26.0,<7.0.0)
Requires-Dist: kaggle (>=1.5.16,<2.0.0)
Requires-Dist: kaleido (==0.2.1)
Requires-Dist: matplotlib (>=3.8.1,<4.0.0)
Requires-Dist: numpy (>=1.26.2,<2.0.0)
Requires-Dist: opencv-python-headless (>=4.8.1.78,<5.0.0.0)
Requires-Dist: pillow (>=10.1.0,<11.0.0)
Requires-Dist: pip (>=23.3.1,<24.0.0)
Requires-Dist: plotly (>=5.18.0,<6.0.0)
Requires-Dist: provae (>=0.1.0,<0.2.0)
Requires-Dist: pytest (>=7.4.3,<8.0.0)
Requires-Dist: pytorch-gan-metrics (>=0.5.3,<0.6.0)
Requires-Dist: rembg (>=2.0.52,<3.0.0)
Requires-Dist: scikit-learn (==1.3.2)
Requires-Dist: torch (>=2.0.0,!=2.0.1,!=2.1.0)
Requires-Dist: torchaudio (>=2.1.0,<3.0.0)
Requires-Dist: torchvision (>=0.16.0,<0.17.0)
